direnv.py
python_direnv-0.2.2.dist-info/WHEEL
python_direnv-0.2.2.dist-info/METADATA
python_direnv-0.2.2.dist-info/RECORD
