Metadata-Version: 2.1
Name: python-direnv
Version: 0.2.2
Summary: Loads environment variables from a direnv .envrc file.
Author-email: Nicolas Graves <ngraves@ngraves.fr>
Requires-Python: >=3.8
Classifier: Programming Language :: Python :: 3
Classifier: License :: OSI Approved :: GNU General Public License v3 (GPLv3)
Classifier: Operating System :: OS Independent
Project-URL: Homepage, https://github.com/nicolas-graves/python-direnv
Project-URL: Issues, https://github.com/nicolas-graves/python-direnv/issues
